exboard/__init__.py
exboard/jetson.py
exboard/rk3390.py
exboard-1.0.12.dist-info/LICENSE
exboard-1.0.12.dist-info/METADATA
exboard-1.0.12.dist-info/WHEEL
exboard-1.0.12.dist-info/top_level.txt
exboard-1.0.12.dist-info/RECORD
