Metadata-Version: 2.1
Name: exboard
Version: 1.0.12
Summary: A exboard package for AIBOX
Author-email: Allen <jiangyangcreate@gmail.com>
Project-URL: Homepage, https://github.com/jiangyangcreate/exboard
Project-URL: Issues, https://github.com/jiangyangcreate/exboard/issues
Classifier: Programming Language :: Python :: 3
Classifier: License :: OSI Approved :: MIT License
Classifier: Operating System :: OS Independent
Requires-Python: >=3.6
License-File: LICENSE
